zwergetl/__init__.py
zwergetl/engine/__init__.py
zwergetl/engine/connections.py
zwergetl/engine/edges.py
zwergetl/engine/enums.py
zwergetl/engine/exceptions.py
zwergetl/engine/graph.py
zwergetl/engine/metadata.py
zwergetl/engine/nodes.py
zwergetl/engine/phase.py
zwergetl/engine/records.py
zwergetl/engine/utils.py
zwergetl/engine/watchdog.py
zwergetl_engine-0.1.11.dist-info/licenses/LICENSE.txt
zwergetl_engine-0.1.11.dist-info/METADATA
zwergetl_engine-0.1.11.dist-info/WHEEL
zwergetl_engine-0.1.11.dist-info/top_level.txt
zwergetl_engine-0.1.11.dist-info/RECORD
