Metadata-Version: 2.4
Name: zwergetl-engine
Version: 0.1.11
Summary: ZwergETL Engine
Maintainer: DX Dataworks
Requires-Python: >=3.6
License-File: LICENSE.txt
Dynamic: license-file
